{   
    "jgchaping":60,
    "jgbanner":30,
    "jgnative":3,
    "name":"KeepHealth",
    "pkg":"com.dongdong.keephealth",
    "channel":"androidjs",
    "sign":"45:87:82:66:3A:DA:1F:71:CC:ED:E5:06:DF:90:1B:53:F8:01:5A:6A",
    "versioni":158,
    "version":"1.5.8",
    "ratiosplash":"gdt-10",
    "ratiobanner":"gdt-10",
    "ratiochaping":"gdt-10",
    "rationative":"gdt-10",
    "ratiorewardvideo":"gdt-10",
    "ratiofullvideo":"gdt-10",
    "gdt":{
    "open":true,
    "appid":"1107884141",
    "splash":"6071306898585267",
    "banner":"8081208818087269",
    "fullvideo":"8091903838082323",
    "chaping":"5091404838884355",
    "nativestxw":"7091104818881308" ,
    "nativeswxt":"2031608808481470",
    "nativeztyw":"2071307868689431",
    "nativezwyt":"4011605838688492",
    "nativestsw":"9001007828287494",
    "nativect1280720":"9081602818980497",
    "nativect8001200":"7011308818389469",
    "nativesxt":"2071405838487571",
    "nativewswxt":"4041702888780542",
    "nativewstxw":"6041801898987515",
    "nativewdt":"9051904868384586",
    "nativect10801920":"6041507848983597",
    "rewardvideo":"7011109848980690"
    },

    "toutiao":{
    "open":false,
    "appid":"",
    "nativeid":"",
    "banner600300":"",
    "banner600400":"",
    "banner600500":"",
    "banner600260":"",
    "banner60090":"",
    "banner600150":"",
    "banner640100":"",
    "banner690388":"",
    "chaping11":"",
    "chaping23":"" ,
    "chaping32":"",
    "fullvideov":"",
    "fullvideoh":"",
    "splash":"",
    "rewardvideov":"",
    "rewardvideoh":"" ,
    "drawvideo":"",
    "nativevideo":""},
    "adview":
    {
        "open":false,
        "appid":"",
         "splash":"",
        "banner":"",
        "chaping":"",
        "native":"",
        "video":"",
        "hudong":"" 
    },
    "mintegral":{
        "open":false,
        "appid":"",
        "splash":"",
        "banner":"",
        "chaping":"",
        "native":"",
        "rewardvideo":""
    }
 
}